yt_ddl/__init__.py
yt_ddl/yt_ddl.py
youtube_dash_dl-1.0.8.dist-info/LICENSE
youtube_dash_dl-1.0.8.dist-info/METADATA
youtube_dash_dl-1.0.8.dist-info/WHEEL
youtube_dash_dl-1.0.8.dist-info/dependency_links.txt
youtube_dash_dl-1.0.8.dist-info/entry_points.txt
youtube_dash_dl-1.0.8.dist-info/top_level.txt
youtube_dash_dl-1.0.8.dist-info/RECORD
