Metadata-Version: 2.1
Name: youtube-dash-dl
Version: 1.0.8
Summary: Tool to download VoD of an ongoing stream without any time limitations.
Home-page: https://github.com/IamEld3st/youtube_dash_dl
Author: IamEld3st
Author-email: iameld3st@gmail.com
License: MIT
Platform: UNKNOWN
Classifier: License :: OSI Approved :: MIT License
Classifier: Programming Language :: Python :: 3.6
Requires-Python: >=3.6
Requires-Dist: av
Requires-Dist: click
Requires-Dist: lxml
Requires-Dist: requests
Requires-Dist: tqdm
Requires-Dist: setuptools
